[
  {
    "title": {
      "jp": "The Forbidden Academy"
    },
    "synopsis": "After being swept away by a magic sword to an unknown yet beautiful world, Yui finds herself in the company of gods with a sacred order bestowed upon her from Zeus himself: strengthen the bonds between man and their deities.",
    "season": 1,
    "number": 1,
    "thumbUrl": "https://media.kitsu.io/episodes/thumbnails/114560/original.jpg",
    "releasedAt": "2014-04-06T00:00:00.000Z",
    "content": {}
  },
  {
    "title": {
      "jp": "Beautiful Shackles"
    },
    "synopsis": "Yui finds out the reasons why herself and her godly classmates have been transported to a school in the skies. In order to get home, they must sufficiently strengthen the bond between man and god by the time they are ready to graduate.",
    "season": 1,
    "number": 2,
    "thumbUrl": "https://media.kitsu.io/episodes/thumbnails/114561/original.jpg",
    "releasedAt": "2014-04-13T00:00:00.000Z",
    "content": {}
  },
  {
    "title": {
      "jp": "Sea Breeze Conflict"
    },
    "synopsis": "Yui and Appolon, desperate to get the delinquent gods to attend school, devise a plan to show them the fun side of school life.",
    "season": 1,
    "number": 3,
    "thumbUrl": "https://media.kitsu.io/episodes/thumbnails/114562/original.jpg",
    "releasedAt": "2014-04-20T00:00:00.000Z",
    "content": {}
  },
  {
    "title": {
      "jp": "The Curse of Hades"
    },
    "synopsis": "The newly formed student council decides to start joining after school activities… all except Hades. With his love of the stars, Yui suggests he join the Astronomy Club, but he coldly refuses. Yui is determined to find out why.",
    "season": 1,
    "number": 4,
    "thumbUrl": "https://media.kitsu.io/episodes/thumbnails/114563/original.jpg",
    "releasedAt": "2014-04-26T00:00:00.000Z",
    "content": {}
  },
  {
    "title": {
      "jp": "The Unforgivable Heart"
    },
    "synopsis": "Takeru, otherwise known as the god Susanoo, is the last hold out yet to engage in any extracurricular activities. With their graduation hanging in the balance, Yui must duel with Takeru to see whether or not he will join a club.",
    "season": 1,
    "number": 5,
    "thumbUrl": "https://media.kitsu.io/episodes/thumbnails/114564/original.jpg",
    "releasedAt": "2014-05-03T00:00:00.000Z",
    "content": {}
  },
  {
    "title": {
      "jp": "The Moonlight's Feelings"
    },
    "synopsis": "Tsukito agrees to prepare a moon viewing for Yui and the rest of the gods. However, overworking himself might undo all of his efforts.",
    "season": 1,
    "number": 6,
    "thumbUrl": "https://media.kitsu.io/episodes/thumbnails/114565/original.jpg",
    "releasedAt": "2014-05-10T00:00:00.000Z",
    "content": {}
  },
  {
    "title": {
      "jp": "Promise of the Frozen Wastes"
    },
    "synopsis": "The seasons suddenly turn, and the students decide to hold a Christmas event. Balder becomes upset after finding out he has to work apart from Yui.",
    "season": 1,
    "number": 7,
    "thumbUrl": "https://media.kitsu.io/episodes/thumbnails/114566/original.jpg",
    "releasedAt": "2014-05-17T00:00:00.000Z",
    "content": {}
  },
  {
    "title": {
      "jp": "The Solitude of Light"
    },
    "synopsis": "Tensions flare at the Christmas market, where Loki and Balder face off in front of Yui.",
    "season": 1,
    "number": 8,
    "thumbUrl": "https://media.kitsu.io/episodes/thumbnails/114567/original.jpg",
    "releasedAt": "2014-05-24T00:00:00.000Z",
    "content": {}
  },
  {
    "title": {
      "jp": "Dark Prison of Scattered Flowers"
    },
    "synopsis": "Yuki and the Gods' mission continues as the year progresses, and little by little the globe is filling up, signaling completion of their task.",
    "season": 1,
    "number": 9,
    "thumbUrl": "https://media.kitsu.io/episodes/thumbnails/114568/original.jpg",
    "releasedAt": "2014-05-31T00:00:00.000Z",
    "content": {}
  },
  {
    "title": {
      "jp": "Lovely and Ephemeral"
    },
    "synopsis": "Yui and her friends put on a version of Cinderella, which turns out nothing like the original thanks to two mischievous gods.",
    "season": 1,
    "number": 10,
    "thumbUrl": "https://media.kitsu.io/episodes/thumbnails/114569/original.jpg",
    "releasedAt": "2014-06-07T00:00:00.000Z",
    "content": {}
  },
  {
    "title": {
      "jp": "Chains of Fate"
    },
    "synopsis": "While Apollon and Yui make sure that Balder is okay after he passes out, they hear through the grapevine that the gods have nothing good planned for Balder.",
    "season": 1,
    "number": 11,
    "thumbUrl": "https://media.kitsu.io/episodes/thumbnails/114570/original.jpg",
    "releasedAt": "2014-06-14T00:00:00.000Z",
    "content": {}
  },
  {
    "title": {
      "jp": "Eternal Separation"
    },
    "synopsis": "Into the dark abyss of the sea goes Balder. Deeper and deeper he plunges into the nothingness all for the benefit of the world. With Loki right behind him, will the light shine through?",
    "season": 1,
    "number": 12,
    "thumbUrl": "https://media.kitsu.io/episodes/thumbnails/114571/original.jpg",
    "releasedAt": "2014-06-21T00:00:00.000Z",
    "content": {}
  }
]