{
  "slug": "giovanni-no-shima",
  "synopsis": "In the aftermath of the most devastating conflict mankind had ever experienced, the tiny island of Shikotan became part of the Sakhalin Oblast... and on the unhealed border in this remote corner of the world, friendship among children from two different countries timidly blossomed, striving to overcome language barriers and the waves of history. Inspired by true events.On August 15th, they told us we had lost the war. At that time, we did not really understand. Then one day, everything changed. Many soldiers, wearing uniforms we had never seen before, arrived on the island. That was the day I met Tanya.\n(Source: Production I.G)",
  "title": {
    "en": "Giovanni's Island",
    "jp": "Giovanni no Shima"
  },
  "releasedAt": "2014-02-22T00:00:00.000Z",
  "finishedAt": "2014-02-22T00:00:00.000Z",
  "kind": "movie",
  "status": "finished",
  "rating": "pg",
  "posterUrl": "https://media.kitsu.io/anime/poster_images/7801/original.jpg",
  "categories": [
    "disaster",
    "drama",
    "family",
    "friendship",
    "historical",
    "past",
    "russia"
  ],
  "externals": [],
  "relations": {
    "kitsu": "7801",
    "anidb": "9921",
    "anilist/anime": "19115",
    "aozora": "uTqWyclOcw",
    "myanimelist/anime": "19115"
  }
}