{
  "slug": "garzey-s-wing",
  "synopsis": "Yesterday, Chris's biggest problem was getting into a good college. Now, his spirit has been hijacked by wings of light, and transported into an ancient world. Summoned by an enslaved tribe to lead a bloody revolution, Chris must quickly adapt to his new surroundings... or die. \n(Source: ANN)",
  "title": {
    "en": "Garzey's Wing",
    "jp": "Byston Well Monogatari: Garzey no Tsubasa"
  },
  "releasedAt": "1996-09-21T00:00:00.000Z",
  "finishedAt": "1997-04-09T00:00:00.000Z",
  "kind": "ova",
  "status": "finished",
  "rating": "pg",
  "posterUrl": "https://media.kitsu.io/anime/poster_images/1488/original.jpg",
  "coverUrl": "https://media.kitsu.io/anime/cover_images/1488/original.jpg",
  "categories": [
    "action",
    "adventure",
    "fantasy",
    "fantasy world",
    "feudal warfare",
    "military",
    "parallel universe",
    "plot continuity",
    "present",
    "super power",
    "swordplay",
    "violence"
  ],
  "externals": [],
  "relations": {
    "kitsu": "1488",
    "anidb": "2330",
    "anilist/anime": "1657",
    "aozora": "r7C1VVWHYY",
    "myanimelist/anime": "1657"
  }
}