{
  "slug": "genki-genki-non-tan",
  "synopsis": "This 3D animated series for young children is based on the adventures of perky white kitten Non-tan. With his friends, fun-loving Tanuki, strong Bear, and the pink Rabbit triplets and his rival, Pig, he teaches children positive lessons about the beauty and wonder of life.\n(Source: The Anime Encyclopedia)",
  "title": {
    "jp": "Genki Genki Non-tan"
  },
  "releasedAt": "2002-11-04T00:00:00.000Z",
  "finishedAt": "2002-12-04T00:00:00.000Z",
  "kind": "tv",
  "status": "finished",
  "rating": "g",
  "posterUrl": "https://media.kitsu.io/anime/poster_images/9277/original.jpg",
  "categories": [
    "kids",
    "music"
  ],
  "externals": [],
  "relations": {
    "kitsu": "9277",
    "anidb": "10170",
    "aozora": "TYd6W80gaj",
    "myanimelist/anime": "25609"
  }
}