{
  "slug": "ima-futari-no-michi",
  "synopsis": "The purpose of the short is to thank people for help during the prefecture's reconstruction efforts and prevent victims' memories of the 2011 disaster from fading away. \nThe anime's story focuses on a pair of 16-year-old high school students who experience the Tohoku disaster and grow in the aftermath. Jun Agatsuma's father is a doctor, and she worries about the future. Kunpei Satou's father is a fisherman, and it was decided that the boy will succeed his father in the job. The pair's lives are suddenly disrupted when the 2011 earthquake and tsunami hit their area. The two determine their futures as Miyagi Prefecture recovers in the wake of the disaster.\nThree people connected to Miyagi Prefecture were chosen to voice the short's characters. \n(Source: ANN)",
  "title": {
    "jp": "Ima, Futari no Michi"
  },
  "releasedAt": "2015-03-08T00:00:00.000Z",
  "finishedAt": "2015-03-08T00:00:00.000Z",
  "kind": "special",
  "status": "finished",
  "rating": "g",
  "posterUrl": "https://media.kitsu.io/anime/poster_images/10669/original.jpg",
  "categories": [
    "drama"
  ],
  "externals": [],
  "relations": {
    "kitsu": "10669",
    "anidb": "11119",
    "anilist/anime": "21877",
    "aozora": "8L8JpB5s4d",
    "myanimelist/anime": "30133"
  }
}