{
  "slug": "omishi-mahou-gekijou-risky-safety",
  "synopsis": "An apprentice shinigami (Japanese Death God), Risky, is determined to take Moe's life. However, Risky is magically joined with an apprentice angel, Safety, so Risky turns into Safety whenever someone says something nice. As an apprentice shinigami can only take someone's life when that person is really depressed, Risky has quite a problem taking Moe's soul, while dealing with Safety, who often cheers Moe up.\n(Source: ANN)",
  "title": {
    "jp": "Omishi Mahou Gekijou: Risky★Safety"
  },
  "releasedAt": "1999-10-05T00:00:00.000Z",
  "finishedAt": "2000-04-04T00:00:00.000Z",
  "kind": "tv",
  "status": "finished",
  "rating": "pg",
  "posterUrl": "https://media.kitsu.io/anime/poster_images/1172/original.jpg",
  "coverUrl": "https://media.kitsu.io/anime/cover_images/1172/original.jpeg",
  "categories": [
    "angel",
    "asia",
    "comedy",
    "contemporary fantasy",
    "demon",
    "earth",
    "fantasy",
    "japan",
    "magic",
    "present",
    "slice of life"
  ],
  "externals": [],
  "relations": {
    "kitsu": "1172",
    "anidb": "971",
    "anilist/anime": "1300",
    "aozora": "FCjEx51BwO",
    "myanimelist/anime": "1300",
    "thetvdb": "120191",
    "trakt": "21191"
  }
}