{
  "slug": "ufo-princess-valkyrie-3-seiresetsu-no-hanayome",
  "synopsis": "The third season doesn`t have a particular story behind everything (like \"Valkyrie Ghost\" in the second season). It just tells 6 stories about the life of Kazuto &amp; Co. with some additions: Raine and Chorus get a house on earth, the last three Valhalla princesses each get an episode, and in the last episode Kazuto and Valkyrie, who in the same episode managed to stay adult, &gt;try&lt; to marry again. \n(Source: ANN)",
  "title": {
    "en": "UFO Ultramaiden Valkyrie 3: Bride of Celestial Souls' Day",
    "jp": "UFO Princess Valkyrie 3: Seiresetsu no Hanayome"
  },
  "releasedAt": "2005-05-25T00:00:00.000Z",
  "finishedAt": "2005-10-25T00:00:00.000Z",
  "kind": "ova",
  "status": "finished",
  "rating": "pg",
  "posterUrl": "https://media.kitsu.io/anime/poster_images/1359/original.jpg",
  "coverUrl": "https://media.kitsu.io/anime/cover_images/1359/original.jpg",
  "categories": [
    "alien",
    "comedy",
    "deity",
    "earth",
    "ecchi",
    "fantasy",
    "juujin",
    "magic",
    "romance",
    "science fiction"
  ],
  "externals": [],
  "relations": {
    "kitsu": "1359",
    "anidb": "2775",
    "anilist/anime": "1514",
    "aozora": "lpNioInKWb",
    "myanimelist/anime": "1514"
  }
}