{
  "slug": "uma-musume-pretty-derby-season-2",
  "synopsis": "Toukai Teiou, who has adored the undefeated Symboli Rudolph and is aiming for the Triple Crown, is attracting attention all over Japan ahead of the upcoming Japan Derby's race.\n\n(Source: Anime News Network)",
  "title": {
    "jp": "Uma Musume: Pretty Derby Season 2"
  },
  "releasedAt": "2021-01-05T00:00:00.000Z",
  "finishedAt": "2021-03-30T00:00:00.000Z",
  "kind": "tv",
  "status": "finished",
  "rating": "pg",
  "posterUrl": "https://media.kitsu.io/anime/poster_images/43576/original.jpg",
  "coverUrl": "https://media.kitsu.io/anime/cover_images/43576/original.jpg",
  "categories": [
    "comedy",
    "juujin",
    "slice of life",
    "sports"
  ],
  "externals": [],
  "relations": {
    "kitsu": "43576",
    "anilist/anime": "124223",
    "myanimelist/anime": "42941"
  }
}