{
  "slug": "warau-arsnotoria-sun",
  "synopsis": "Here in this magic academy city of Ashram, where everyone is required to live in dormitories, a close-knit group of girls known as \"Pentagrams\" pursue their studies, including training in manners and magic, to become \"true ladies.\" Arsnotoria, one of the students in Ashram, lives in Dorm 5 and is always with her dormmate friends: Mel, who's the life of the party, Petit Albert, who's quiet and does things at her own pace, Picatrix, who wants to be the class president, and Abramelin, who's always cool. They take classes and work on their school duties together, and they throw tea parties after school in \"that room\"... We'll share the girls' fun and lively days with you!\n\n(Source: Crunchyroll)",
  "title": {
    "en": "Smile of the Arsnotoria the Animation",
    "jp": "Warau Arsnotoria Sun!"
  },
  "releasedAt": "2022-07-06T00:00:00.000Z",
  "finishedAt": "1970-01-01T00:00:00.000Z",
  "kind": "tv",
  "status": "upcoming",
  "rating": "pg",
  "posterUrl": "https://media.kitsu.io/anime/46136/poster_image/051bc59616de6c5e68f0a559d23517cc.jpg",
  "categories": [
    "fantasy",
    "slice of life"
  ],
  "externals": [],
  "relations": {
    "kitsu": "46136",
    "anilist/anime": "149874",
    "myanimelist/anime": "51923"
  }
}