{
  "slug": "origami-of-landscape",
  "synopsis": "An animation of landscapes fluidly changing shapes.",
  "title": {
    "jp": "Origami of Landscape"
  },
  "releasedAt": "2013-06-08T00:00:00.000Z",
  "finishedAt": "2013-06-08T00:00:00.000Z",
  "kind": "ona",
  "status": "finished",
  "rating": "g",
  "posterUrl": "https://media.kitsu.io/anime/poster_images/12972/original.jpg",
  "categories": [],
  "externals": [],
  "relations": {
    "kitsu": "12972",
    "anilist/anime": "103445",
    "aozora": "vSZ5ZSWsSn",
    "myanimelist/anime": "34633"
  }
}