{
  "slug": "alice-in-deadly-school",
  "synopsis": "The story begins with the peaceful daily life of schoolgirls—which suddenly breaks down when former schoolmates become zombies. The story follows the actions taken by the girls left behind on the school roof.\n\n(Source: ANN)\n\nNote: Note: The first half aired on Jan 4, 2021 as part of a New Year's special alongside the first episode of Gekidol.",
  "title": {
    "en": "",
    "jp": "Alice in Deadly School"
  },
  "releasedAt": "2021-03-03T00:00:00.000Z",
  "finishedAt": "2021-03-03T00:00:00.000Z",
  "kind": "ova",
  "status": "finished",
  "rating": "pg",
  "posterUrl": "https://media.kitsu.io/anime/poster_images/12541/original.jpg",
  "categories": [
    "comedy",
    "school life"
  ],
  "externals": [],
  "relations": {
    "kitsu": "12541",
    "anidb": "12330",
    "anilist/anime": "21569",
    "aozora": "S0Jh16Wsqm",
    "myanimelist/anime": "33839"
  }
}