{
  "slug": "hai-akko-desu",
  "synopsis": "The story follows the daily life of a Akko-chan who is a new young wife.",
  "title": {
    "jp": "Hai! Akko Desu"
  },
  "releasedAt": "1988-10-12T00:00:00.000Z",
  "finishedAt": "1992-03-26T00:00:00.000Z",
  "kind": "tv",
  "status": "finished",
  "rating": "g",
  "posterUrl": "https://media.kitsu.io/anime/poster_images/4139/original.jpg",
  "categories": [
    "housewives",
    "romance",
    "slice of life"
  ],
  "externals": [],
  "relations": {
    "kitsu": "4139",
    "anidb": "5960",
    "anilist/anime": "5534",
    "aozora": "4tFC4W1hXo",
    "myanimelist/anime": "5534"
  }
}