[
  {
    "title": {
      "jp": "Karen Bee Sono Ichi"
    },
    "synopsis": "The five girls' problems with supernatural beings have been solved, and it's now summer break, with the culture fair over. Koyomi Araragi has two little sisters, self-proclaimed \"heroes\" nicknamed the Fire Sisters, Karen and Tsukihi.",
    "season": 1,
    "number": 1,
    "thumbUrl": "https://media.kitsu.io/episodes/thumbnails/172011/original.jpeg",
    "releasedAt": "2012-01-08T00:00:00.000Z",
    "content": {}
  },
  {
    "title": {
      "jp": "Karen Bee Sono Ni"
    },
    "synopsis": "Temptation haunts Koyomi, while visiting Sengoku he is presented with several tempting offers. After surviving each one, his visit to Kanbaru continues to put him in compromising situations.",
    "season": 1,
    "number": 2,
    "thumbUrl": "https://media.kitsu.io/episodes/thumbnails/172012/original.jpeg",
    "releasedAt": "2012-01-15T00:00:00.000Z",
    "content": {}
  },
  {
    "title": {
      "jp": "Karen Bee Sono San"
    },
    "synopsis": "Araragi leaves Kanbaru's house and meets a dangerous man named Kaiki. While following him, he runs into Senjougahara, who berates him for skipping his studies.",
    "season": 1,
    "number": 3,
    "thumbUrl": "https://media.kitsu.io/episodes/thumbnails/172013/original.jpeg",
    "releasedAt": "2012-01-21T00:00:00.000Z",
    "content": {}
  },
  {
    "title": {
      "jp": "Karen Bee Sono Yon"
    },
    "synopsis": "Karen is badly ill, having been poisoned by an evil, supernatural bee. Will Koyomi BEE able to cure her in time?",
    "season": 1,
    "number": 4,
    "thumbUrl": "https://media.kitsu.io/episodes/thumbnails/172014/original.jpeg",
    "releasedAt": "2012-01-28T00:00:00.000Z",
    "content": {}
  },
  {
    "title": {
      "jp": "Karen Bee Sono Go"
    },
    "synopsis": "Koyomi learns the whole story about what happened between Karen and Kaiki. After receiving a tempting offer from Hanekawa, he speaks with Shinobu on the way to save Karen.",
    "season": 1,
    "number": 5,
    "thumbUrl": "https://media.kitsu.io/episodes/thumbnails/172015/original.jpeg",
    "releasedAt": "2012-02-05T00:00:00.000Z",
    "content": {}
  },
  {
    "title": {
      "jp": "Karen Bee Sono Roku"
    },
    "synopsis": "Koyomi leaves Karen behind at home to talk with Senjougahara. Senjougahara seems to be planning on confronting and murdering Kaiki. When he comes back home, he learns Karen has wandered off, while still sick.",
    "season": 1,
    "number": 6,
    "thumbUrl": "https://media.kitsu.io/episodes/thumbnails/172016/original.jpeg",
    "releasedAt": "2012-02-12T00:00:00.000Z",
    "content": {}
  },
  {
    "title": {
      "jp": "Karen Bee Sono Nana"
    },
    "synopsis": "Araragi goes to confront Kaiki and stop him from leaving the city. But Kaiki is wiley and smart, and not easily dissuaded when there's money on the line.",
    "season": 1,
    "number": 7,
    "thumbUrl": "https://media.kitsu.io/episodes/thumbnails/172017/original.jpeg",
    "releasedAt": "2012-02-19T00:00:00.000Z",
    "content": {}
  },
  {
    "title": {
      "jp": "Tsukihi Phoenix, Sono Ichi"
    },
    "synopsis": "Karen is acting clingy and very cute, completely out of character. But its a trick to get Koyomi to introduce her to Kanbaru. In response, he devises a test Karen must pass; a test involving her toothbrush.",
    "season": 1,
    "number": 8,
    "thumbUrl": "https://media.kitsu.io/episodes/thumbnails/172018/original.jpeg",
    "releasedAt": "2012-02-26T00:00:00.000Z",
    "content": {}
  },
  {
    "title": {
      "jp": "Tsukihi Phoenix, Sono Ni"
    },
    "synopsis": "While taking Karen to meet Kanbaru, Araragi is put into a compromising position. On the way, he runs into someone asking about familiar things.",
    "season": 1,
    "number": 9,
    "thumbUrl": "https://media.kitsu.io/episodes/thumbnails/172019/original.jpeg",
    "releasedAt": "2012-03-04T00:00:00.000Z",
    "content": {}
  },
  {
    "title": {
      "jp": "Tsukihi Phoenix, Sono San"
    },
    "synopsis": "Araragi agrees to take Shinobu on a trip to buy doughnuts. At the restaurant, an old acquaintance is able to give information on the town's new visitors.",
    "season": 1,
    "number": 10,
    "thumbUrl": "https://media.kitsu.io/episodes/thumbnails/172020/original.jpeg",
    "releasedAt": "2012-03-11T00:00:00.000Z",
    "content": {}
  },
  {
    "title": {
      "jp": "Tsukihi Phoenix, Sono Yon"
    },
    "synopsis": "As Shinobu explains how Tsukihi came to be in her currents situation. Araragi resolves to stop the out-of-towners from killing her. But unlike Oshino and Kaiki, Kagenui speaks with her fist and she talks a lot.",
    "season": 1,
    "number": 11,
    "thumbUrl": "https://media.kitsu.io/episodes/thumbnails/172021/original.jpeg",
    "releasedAt": "2012-03-18T00:00:00.000Z",
    "content": {}
  }
]