[
  {
    "id": "304314",
    "title": {},
    "season": 1,
    "number": 1,
    "content": {}
  },
  {
    "id": "304315",
    "title": {},
    "season": 1,
    "number": 2,
    "content": {}
  },
  {
    "id": "304316",
    "title": {},
    "season": 1,
    "number": 3,
    "content": {}
  },
  {
    "id": "304317",
    "title": {},
    "season": 1,
    "number": 4,
    "content": {}
  },
  {
    "id": "304318",
    "title": {},
    "season": 1,
    "number": 5,
    "content": {}
  },
  {
    "id": "304319",
    "title": {},
    "season": 1,
    "number": 6,
    "content": {}
  },
  {
    "id": "304320",
    "title": {},
    "season": 1,
    "number": 7,
    "content": {}
  },
  {
    "id": "304321",
    "title": {},
    "season": 1,
    "number": 8,
    "content": {}
  },
  {
    "id": "304322",
    "title": {},
    "season": 1,
    "number": 9,
    "content": {}
  },
  {
    "id": "304323",
    "title": {},
    "season": 1,
    "number": 10,
    "content": {}
  },
  {
    "id": "304324",
    "title": {},
    "season": 1,
    "number": 11,
    "content": {}
  },
  {
    "id": "304325",
    "title": {},
    "season": 1,
    "number": 12,
    "content": {}
  },
  {
    "id": "304326",
    "title": {},
    "season": 1,
    "number": 13,
    "content": {}
  },
  {
    "id": "304327",
    "title": {},
    "season": 1,
    "number": 14,
    "content": {}
  },
  {
    "id": "304328",
    "title": {},
    "season": 1,
    "number": 15,
    "content": {}
  },
  {
    "id": "304329",
    "title": {},
    "season": 1,
    "number": 16,
    "content": {}
  },
  {
    "id": "304330",
    "title": {},
    "season": 1,
    "number": 17,
    "content": {}
  },
  {
    "id": "304331",
    "title": {},
    "season": 1,
    "number": 18,
    "content": {}
  },
  {
    "id": "304332",
    "title": {},
    "season": 1,
    "number": 19,
    "content": {}
  },
  {
    "id": "304333",
    "title": {},
    "season": 1,
    "number": 20,
    "content": {}
  },
  {
    "id": "304334",
    "title": {},
    "season": 1,
    "number": 21,
    "content": {}
  },
  {
    "id": "304335",
    "title": {},
    "season": 1,
    "number": 22,
    "content": {}
  },
  {
    "id": "304336",
    "title": {},
    "season": 1,
    "number": 23,
    "content": {}
  },
  {
    "id": "304337",
    "title": {},
    "season": 1,
    "number": 24,
    "content": {}
  }
]