[
  {
    "id": "303558",
    "title": {},
    "season": 1,
    "number": 1,
    "content": {}
  },
  {
    "id": "303559",
    "title": {},
    "season": 1,
    "number": 2,
    "content": {}
  },
  {
    "id": "303560",
    "title": {},
    "season": 1,
    "number": 3,
    "content": {}
  },
  {
    "id": "303561",
    "title": {},
    "season": 1,
    "number": 4,
    "content": {}
  },
  {
    "id": "303562",
    "title": {},
    "season": 1,
    "number": 5,
    "content": {}
  },
  {
    "id": "303563",
    "title": {},
    "season": 1,
    "number": 6,
    "content": {}
  },
  {
    "id": "303564",
    "title": {},
    "season": 1,
    "number": 7,
    "content": {}
  },
  {
    "id": "303565",
    "title": {},
    "season": 1,
    "number": 8,
    "content": {}
  },
  {
    "id": "303566",
    "title": {},
    "season": 1,
    "number": 9,
    "content": {}
  },
  {
    "id": "303567",
    "title": {},
    "season": 1,
    "number": 10,
    "content": {}
  },
  {
    "id": "303568",
    "title": {},
    "season": 1,
    "number": 11,
    "content": {}
  },
  {
    "id": "303569",
    "title": {},
    "season": 1,
    "number": 12,
    "content": {}
  },
  {
    "id": "303570",
    "title": {},
    "season": 1,
    "number": 13,
    "content": {}
  },
  {
    "id": "303571",
    "title": {},
    "season": 1,
    "number": 14,
    "content": {}
  },
  {
    "id": "303572",
    "title": {},
    "season": 1,
    "number": 15,
    "content": {}
  },
  {
    "id": "303573",
    "title": {},
    "season": 1,
    "number": 16,
    "content": {}
  }
]