{
  "slug": "dungeon-meshi-senshi-no-kantan-cooking",
  "synopsis": "Promotional videos with original animation for Dungeon Meshi.\n\nThe first episode is a stop-motion short in honor of the 5th tankoubon going on sale. It features Senshi's hands trying to prepare a walking mushroom. It is the same walking mushroom as shown in the manga's 1st volume in the \"Monster Tidbits\" bonus chapter.\n\nThe second episode is a traditional animated short in honor of the 8th tankoubon going on sale.\n\n(Source: MAL)",
  "title": {
    "jp": "Dungeon Meshi: Senshi no Kantan Cooking!"
  },
  "releasedAt": "2017-07-31T00:00:00.000Z",
  "finishedAt": "2019-09-04T00:00:00.000Z",
  "kind": "ona",
  "status": "finished",
  "rating": "g",
  "posterUrl": "https://media.kitsu.io/anime/poster_images/40976/original.jpg",
  "categories": [
    "comedy",
    "cooking",
    "fantasy"
  ],
  "externals": [],
  "relations": {
    "kitsu": "40976",
    "anilist/anime": "111516",
    "aozora": "V1i5Esp4yX",
    "myanimelist/anime": "36577"
  }
}