{
  "slug": "bakuto-sengen-daigander",
  "synopsis": "Akira Akebono, a young boy who is competing in a robot tournament where many of the robots are capable of transforming into animal forms. Akira wants to win the ultimate prize, the Titan Belt, with the help of his group of robots, all of which are capable of forming into the robot Daigunder. Daigunder is the creation of Akira's father, Professor Hajime Akebono. Together with a girl named Haruka, they compete under the name of Team Akira. However, Team Akira faces opposition from not only their competition, but a robot named Ginzan who is under the control of the evil Professor Maelstrom.\n(Source: ANN)",
  "title": {
    "en": "Daigunder",
    "jp": "Bakutou Sengen Daigunder"
  },
  "releasedAt": "2002-04-05T00:00:00.000Z",
  "finishedAt": "2002-12-27T00:00:00.000Z",
  "kind": "tv",
  "status": "finished",
  "rating": "pg",
  "posterUrl": "https://media.kitsu.io/anime/poster_images/2897/original.jpg",
  "categories": [
    "action",
    "adventure",
    "mecha",
    "robot",
    "science fiction",
    "super robot"
  ],
  "externals": [],
  "relations": {
    "kitsu": "2897",
    "anidb": "920",
    "anilist/anime": "3271",
    "aozora": "LqTb4f7HTR",
    "myanimelist/anime": "3271"
  }
}