[
  {
    "id": "187239",
    "title": {
      "jp": "Boys Meet Girl"
    },
    "synopsis": "Gandara Music's new A&amp;R Sumisora Tsubasa is assigned to work with the three-group and ten-man idol unit \"B-PROJECT.\" Meeting the boys for the first time while they're rehearsing for a music program, she's immediately toyed with and tossed about by the quirky members of B-PROJECT. Next she accompanies Kitakore, one the groups, to the recording session of their new song. Tsubasa is enchanted by the voices of Kitakado and Korekuni, but during the song, she notices something is off.",
    "season": 1,
    "number": 1,
    "releasedAt": "2016-07-03T00:00:00.000Z",
    "content": {}
  },
  {
    "id": "187240",
    "title": {
      "jp": "Bad End mo Warukunai"
    },
    "synopsis": "During THRIVE's production meeting for their new song, Kaneshiro expresses dissatisfaction over the song's arrangement. He's unable to see the point in pandering to fans any more than necessary. Meanwhile, THRIVE is hired for a gravure shoot for idol magazine \"Kiss &amp; Hug.\" When the chief editor Yoko Suzuki orders him to wear cat ears and make a kitty cat pose, Ashu and Aizome comply, but unable to stand it, Kaneshiro leaves the building.",
    "season": 1,
    "number": 2,
    "releasedAt": "2016-07-10T00:00:00.000Z",
    "content": {}
  },
  {
    "id": "187241",
    "title": {
      "jp": "Brilliant de Ikou"
    },
    "synopsis": "MooNs has arrived at a campsite in the mountains to shoot a commercial for \"Star Curry.\" Because this is the first time one of their songs will be used in a commercial, the members are exited and getting along well. The director Ninomiya expects much from the boys, but the rest of his staff are skeptical. When Tsubasa hears them talking about MooNs, she hopes the job will teach them just how great MooNs is. However, while the shoot starts off well, a problem suddenly occurs.",
    "season": 1,
    "number": 3,
    "releasedAt": "2016-07-17T00:00:00.000Z",
    "content": {}
  },
  {
    "id": "187242",
    "title": {},
    "season": 1,
    "number": 4,
    "content": {}
  },
  {
    "id": "187243",
    "title": {},
    "season": 1,
    "number": 5,
    "content": {}
  },
  {
    "id": "187244",
    "title": {},
    "season": 1,
    "number": 6,
    "content": {}
  },
  {
    "id": "187245",
    "title": {},
    "season": 1,
    "number": 7,
    "content": {}
  },
  {
    "id": "187246",
    "title": {},
    "season": 1,
    "number": 8,
    "content": {}
  },
  {
    "id": "187247",
    "title": {},
    "season": 1,
    "number": 9,
    "content": {}
  },
  {
    "id": "187248",
    "title": {},
    "season": 1,
    "number": 10,
    "content": {}
  },
  {
    "id": "187249",
    "title": {},
    "season": 1,
    "number": 11,
    "content": {}
  },
  {
    "id": "187250",
    "title": {},
    "season": 1,
    "number": 12,
    "content": {}
  }
]