{
  "slug": "miraculous-ladybug-season-2",
  "synopsis": "",
  "title": {
    "en": "Miraculous: Tales of Ladybug and Cat Noir Season 2"
  },
  "releasedAt": "2016-12-11T00:00:00.000Z",
  "finishedAt": "2018-11-18T00:00:00.000Z",
  "kind": "tv",
  "status": "finished",
  "rating": "g",
  "posterUrl": "https://media.kitsu.io/anime/poster_images/13425/original.jpg",
  "coverUrl": "https://media.kitsu.io/anime/13425/cover_image/67292b7a034b0c8483eb00b960cf5f1e.png",
  "categories": [
    "action",
    "anime influenced",
    "comedy",
    "henshin",
    "magical girl",
    "romance",
    "super power"
  ],
  "externals": [],
  "relations": {
    "kitsu": "13425",
    "thetvdb": "302218/2"
  }
}