{
  "slug": "tamayura-sotsugyou-shashin-part-3",
  "synopsis": "The third movie of a four-part finale of Tamayura.",
  "title": {
    "jp": "Tamayura: Sotsugyou Shashin Part 3 - Akogare"
  },
  "releasedAt": "2015-11-28T00:00:00.000Z",
  "finishedAt": "2015-11-28T00:00:00.000Z",
  "kind": "movie",
  "status": "finished",
  "rating": "g",
  "posterUrl": "https://media.kitsu.io/anime/poster_images/10440/original.png",
  "coverUrl": "https://media.kitsu.io/anime/cover_images/10440/original.jpg",
  "categories": [
    "comedy",
    "drama",
    "slice of life"
  ],
  "externals": [],
  "relations": {
    "kitsu": "10440",
    "anilist/anime": "21324",
    "aozora": "uF6270YrlR",
    "myanimelist/anime": "29830"
  }
}