{
  "slug": "thermae-romae",
  "synopsis": "The story is a comedy about Lucius, an architect of public bath houses in ancient Rome, who time-travels to various modern-day baths in Japan. The author explores the two cultures in the world \"that have loved baths the most: the Japanese and the Romans.\" \nPlease note that MAL considers this show to be 3 episodes and not 5. See More Info for additional details. \n(Source: Wikipedia) ",
  "title": {
    "jp": "Thermae Romae"
  },
  "releasedAt": "2012-01-13T00:00:00.000Z",
  "finishedAt": "2012-01-27T00:00:00.000Z",
  "kind": "tv",
  "status": "finished",
  "rating": "pg",
  "posterUrl": "https://media.kitsu.io/anime/poster_images/6705/original.jpg",
  "coverUrl": "https://media.kitsu.io/anime/cover_images/6705/original.jpg",
  "categories": [
    "asia",
    "comedy",
    "europe",
    "historical",
    "italy",
    "japan",
    "present",
    "time travel"
  ],
  "externals": [
    "https://www.crunchyroll.com/thermae-romae"
  ],
  "relations": {
    "kitsu": "6705",
    "anidb": "8831",
    "anilist/anime": "12321",
    "aozora": "A5hkPFpzKy",
    "myanimelist/anime": "12321",
    "thetvdb": "255382/1",
    "thetvdb/series": "255382",
    "trakt": "65688"
  }
}