{
  "slug": "wakame-buildings",
  "synopsis": "Abstract short film by Kojirou Shishido featuring seaweed and sea urchins.",
  "title": {
    "en": "Seaweed Buildings",
    "jp": "Wakame Buildings"
  },
  "releasedAt": "2007-07-25T00:00:00.000Z",
  "finishedAt": "2007-07-25T00:00:00.000Z",
  "kind": "ona",
  "status": "finished",
  "rating": "g",
  "posterUrl": "https://media.kitsu.io/anime/poster_images/44482/original.jpg",
  "categories": [
    "dementia",
    "music"
  ],
  "externals": [],
  "relations": {
    "kitsu": "44482",
    "anilist/anime": "127888",
    "myanimelist/anime": "45616"
  }
}