[
  {
    "id": "175093",
    "title": {},
    "season": 1,
    "number": 1,
    "content": {}
  },
  {
    "id": "175094",
    "title": {},
    "season": 1,
    "number": 2,
    "content": {}
  },
  {
    "id": "175095",
    "title": {},
    "season": 1,
    "number": 3,
    "content": {}
  },
  {
    "id": "175096",
    "title": {},
    "season": 1,
    "number": 4,
    "content": {}
  },
  {
    "id": "175097",
    "title": {},
    "season": 1,
    "number": 5,
    "content": {}
  },
  {
    "id": "175098",
    "title": {},
    "season": 1,
    "number": 6,
    "content": {}
  },
  {
    "id": "175099",
    "title": {},
    "season": 1,
    "number": 7,
    "content": {}
  },
  {
    "id": "175100",
    "title": {},
    "season": 1,
    "number": 8,
    "content": {}
  },
  {
    "id": "175101",
    "title": {},
    "season": 1,
    "number": 9,
    "content": {}
  },
  {
    "id": "175102",
    "title": {},
    "season": 1,
    "number": 10,
    "content": {}
  },
  {
    "id": "175103",
    "title": {},
    "season": 1,
    "number": 11,
    "content": {}
  },
  {
    "id": "175104",
    "title": {},
    "season": 1,
    "number": 12,
    "content": {}
  },
  {
    "id": "175105",
    "title": {},
    "season": 1,
    "number": 13,
    "content": {}
  },
  {
    "id": "175106",
    "title": {},
    "season": 1,
    "number": 14,
    "content": {}
  },
  {
    "id": "175107",
    "title": {},
    "season": 1,
    "number": 15,
    "content": {}
  },
  {
    "id": "175108",
    "title": {},
    "season": 1,
    "number": 16,
    "content": {}
  },
  {
    "id": "175109",
    "title": {},
    "season": 1,
    "number": 17,
    "content": {}
  },
  {
    "id": "175110",
    "title": {},
    "season": 1,
    "number": 18,
    "content": {}
  },
  {
    "id": "175111",
    "title": {},
    "season": 1,
    "number": 19,
    "content": {}
  },
  {
    "id": "175112",
    "title": {},
    "season": 1,
    "number": 20,
    "content": {}
  }
]