{
  "slug": "pokemon-pikachu-and-pichu",
  "synopsis": "Pikachu meets the Pichu brothers and goes on an adventure through the city with them while trying to get back to the building where the rest of Ash's Pokemon are.",
  "title": {
    "en": "Pokemon: Pikachu and Pichu",
    "jp": "Pokemon: Pichu to Pikachu"
  },
  "releasedAt": "2000-07-08T00:00:00.000Z",
  "finishedAt": "2000-07-08T00:00:00.000Z",
  "kind": "movie",
  "status": "finished",
  "rating": "pg",
  "posterUrl": "https://media.kitsu.io/anime/poster_images/3787/original.jpg",
  "categories": [
    "adventure",
    "comedy",
    "fantasy",
    "kids"
  ],
  "externals": [],
  "relations": {
    "kitsu": "3787",
    "anidb": "6798",
    "anilist/anime": "4793",
    "aozora": "M6xE9UyRar",
    "myanimelist/anime": "4793"
  }
}