{
  "slug": "lico-gli",
  "synopsis": "Glico, the prominent food manufacturer best known for its pretzel stick snacks Pocky and Pretz, has long relied on its classic running man character and real-life celebrities to promote its products. Now it has finally bowed to prevailing trends and introduced two moe-style anime characters to broadcast its message.\nLico and Gli are twin brother and sister magicians dedicated to making the world tastier. A newly posted music video has Lico sing (via Vocaloid) about granting everyone's wishes with her sparkly magic.\n(Source: ANN)",
  "title": {
    "en": "The Wizard of twins LICO & GLI",
    "jp": "Futago no Mahoutsukai Lico to Gli"
  },
  "releasedAt": "2013-11-04T00:00:00.000Z",
  "finishedAt": "2015-04-03T00:00:00.000Z",
  "kind": "ona",
  "status": "finished",
  "rating": "g",
  "posterUrl": "https://media.kitsu.io/anime/poster_images/8886/original.jpg",
  "coverUrl": "https://media.kitsu.io/anime/cover_images/8886/original.png",
  "categories": [
    "magic",
    "music"
  ],
  "externals": [],
  "relations": {
    "kitsu": "8886",
    "aozora": "LeKFHzpGzC",
    "myanimelist/anime": "25293"
  }
}