{
  "slug": "fake-identity",
  "synopsis": "Lin Qinghan's grandfather is at stake, but regardless of the stability of the Lin Group, the relatives use all kinds of despicable ways to frame the female president Lin Qinghan and fight for the family property. However, the son-in-law, Zhang Xuan who is called Satan, the lord of the Dragon King Palace, solves the problem one by one.\n\n(Source: Official Youtube Video)",
  "title": {
    "en": "Fake Identity"
  },
  "releasedAt": "2021-04-30T00:00:00.000Z",
  "finishedAt": "2022-03-04T00:00:00.000Z",
  "kind": "ona",
  "status": "finished",
  "rating": "pg",
  "posterUrl": "https://media.kitsu.io/anime/45836/poster_image/38cd8e95aaa0ac0a1ea11c4099f4d783.png",
  "categories": [
    "action",
    "comedy",
    "harem",
    "romance"
  ],
  "externals": [],
  "relations": {
    "kitsu": "45836"
  }
}