{
  "slug": "black-jack-futari-no-kuroi-isha",
  "synopsis": "The mega-corporate Daedalus Group is under attack by a small group of activists known as the Ghost of Icarus. While taking care of some of the victims of the bombing, Black Jack encounters Dr. Kiriko, also known as Death Incarnate, who just like him, asks his patients huge sums of money but instead of saving them, he offers them a painless death. When the activist group requests both doctors’ collaboration, Black Jack finds himself caught in a spiral of life, death and treason while trying to save his patients' lives and avoid the breaking of a biological war that could destroy humanity.\n(Source: ANN)",
  "title": {
    "jp": "Black Jack: Futari no Kuroi Isha"
  },
  "releasedAt": "2005-12-17T00:00:00.000Z",
  "finishedAt": "2005-12-17T00:00:00.000Z",
  "kind": "movie",
  "status": "finished",
  "rating": "pg",
  "posterUrl": "https://media.kitsu.io/anime/poster_images/1785/original.jpg",
  "categories": [
    "action",
    "asia",
    "earth",
    "japan",
    "kyoto"
  ],
  "externals": [],
  "relations": {
    "kitsu": "1785",
    "anidb": "3506",
    "anilist/anime": "1983",
    "aozora": "hUYod7dtfB",
    "myanimelist/anime": "1983"
  }
}