{
  "slug": "top-wo-nerae-3",
  "synopsis": "",
  "title": {
    "en": "Aim for the Top! 3",
    "jp": "Top wo Nerae 3!"
  },
  "kind": "ova",
  "status": "tba",
  "rating": "r",
  "posterUrl": "https://media.kitsu.io/anime/poster_images/42716/original.jpg",
  "categories": [
    "action",
    "comedy",
    "drama",
    "future",
    "mecha",
    "science fiction",
    "space"
  ],
  "externals": [],
  "relations": {
    "kitsu": "42716",
    "anilist/anime": "115006",
    "myanimelist/anime": "38273"
  }
}