{
  "slug": "hotaru-no-mure",
  "synopsis": "This short animated video is a promotional film for the Japanese fiction novel series Fireflies.\n\nFireflies (Hotaru-no-Mure) is an action-packed thriller about an ancient underground orphanage that secretly spawns deadly assassins known only as \"Koma.\" Kitami, a normal fourteen year-old girl accidentally witnesses a Koma killing someone in the woods. Now she is the target of the orphanage — and the only person who can save her is Eiji, the unwilling, shy boy that sits next to her at school.\n\n(Source: Vimeo)",
  "title": {
    "en": "Fireflies",
    "jp": "Hotaru no Mure"
  },
  "releasedAt": "2012-11-11T00:00:00.000Z",
  "finishedAt": "2012-11-11T00:00:00.000Z",
  "kind": "ona",
  "status": "finished",
  "rating": "g",
  "posterUrl": "https://media.kitsu.io/anime/poster_images/11776/original.png",
  "coverUrl": "https://media.kitsu.io/anime/cover_images/11776/original.jpg",
  "categories": [
    "thriller"
  ],
  "externals": [],
  "relations": {
    "kitsu": "11776"
  }
}