{
  "slug": "prism-season",
  "synopsis": "In a gentle adaptation of Megume Nagata's book Flowers Wait for the Moon, a girl grows up, falls in love, and becomes a mother, realizing that her childhood is now forever behind her.   \n(Source: The Anime Encyclopedia)",
  "title": {
    "jp": "Prism Season"
  },
  "releasedAt": "1989-04-21T00:00:00.000Z",
  "finishedAt": "1989-04-21T00:00:00.000Z",
  "kind": "ova",
  "status": "finished",
  "rating": "g",
  "posterUrl": "https://media.kitsu.io/anime/poster_images/40629/original.jpg",
  "categories": [],
  "externals": [],
  "relations": {
    "kitsu": "40629",
    "anilist/anime": "130742",
    "aozora": "4f3eeogQyx",
    "myanimelist/anime": "34868"
  }
}