{
  "slug": "channel-5-5",
  "synopsis": "Channel 5.5's first series of spoofs parodies Kindaichi Case Files.\n(Source: Crunchyroll)",
  "title": {
    "jp": "Channel 5.5"
  },
  "releasedAt": "2014-01-28T00:00:00.000Z",
  "finishedAt": "2014-03-10T00:00:00.000Z",
  "kind": "ona",
  "status": "finished",
  "rating": "pg",
  "posterUrl": "https://media.kitsu.io/anime/poster_images/10378/original.jpg",
  "categories": [
    "comedy",
    "parody"
  ],
  "externals": [],
  "relations": {
    "kitsu": "10378",
    "anidb": "12388",
    "aozora": "ULRYOjCtLC",
    "myanimelist/anime": "29821"
  }
}