{
  "slug": "hello-kitty-and-friends-supercute-adventures",
  "synopsis": null,
  "title": {
    "en": "Hello Kitty and Friends Supercute Adventures"
  },
  "releasedAt": "2020-10-20T00:00:00.000Z",
  "kind": "ona",
  "status": "current",
  "rating": "g",
  "posterUrl": "https://media.kitsu.io/anime/poster_images/43729/original.jpg",
  "coverUrl": "https://media.kitsu.io/anime/cover_images/43729/original.jpg",
  "categories": [
    "anthropomorphism",
    "fantasy",
    "kids",
    "slice of life"
  ],
  "externals": [
    "https://www.youtube.com/watch?v=q0JcAC9UREY&list=PLN9X97LDR0Xvd1KFi7lPT_hqJSVJXYZtE"
  ],
  "relations": {
    "kitsu": "43729",
    "imdb/episodes": "tt13352178"
  }
}