{
  "slug": "dennou-sentai-voogie-s-angel-gaiden-susume-super-angels",
  "synopsis": "SD parody version of Voogie's Angel based on its radio drama of the same name.",
  "title": {
    "jp": "Dennou Sentai Voogie's★Angel Gaiden: Susume! Super★Angels!"
  },
  "releasedAt": "1998-08-21T00:00:00.000Z",
  "finishedAt": "1998-09-19T00:00:00.000Z",
  "kind": "ova",
  "status": "finished",
  "rating": "pg",
  "posterUrl": "https://media.kitsu.io/anime/poster_images/8932/original.jpg",
  "categories": [
    "action",
    "comedy",
    "mecha",
    "parody",
    "science fiction",
    "super deformed"
  ],
  "externals": [],
  "relations": {
    "kitsu": "8932",
    "anidb": "7201",
    "anilist/anime": "118245",
    "aozora": "CjHdJw82y6",
    "myanimelist/anime": "23855"
  }
}