{
  "slug": "gakuen-handsome",
  "synopsis": "The school love story is set at Baramon High School, a private boys' school for the prefecture's most elite. The protagonist is a seventeen year old boy who transfers into the school and meets various major players on campus, such as the outlaw teacher, the soccer captain, and a childhood friend whom the protagonist has not seen for seven years. The school presents opportunities for friendship, love and conflict, and changes are now bound to happen in the main character's life.\n(Source: ANN)",
  "title": {
    "en": "Gakuen Handsome",
    "jp": "Gakuen Handsome"
  },
  "releasedAt": "2016-10-04T00:00:00.000Z",
  "finishedAt": "2016-12-20T00:00:00.000Z",
  "kind": "tv",
  "status": "finished",
  "rating": "pg",
  "posterUrl": "https://media.kitsu.io/anime/poster_images/12482/original.jpg",
  "coverUrl": "https://media.kitsu.io/anime/cover_images/12482/original.jpg",
  "categories": [
    "comedy",
    "parody",
    "school life",
    "shounen ai"
  ],
  "externals": [
    "http://www.crunchyroll.com/gakuen-handsome"
  ],
  "relations": {
    "kitsu": "12482",
    "anidb": "12192",
    "anilist/anime": "21837",
    "aozora": "3n0rENBMdE",
    "myanimelist/anime": "33392",
    "thetvdb": "317830/1"
  }
}