{
  "slug": "kaitou-lupin-813-no-nazo",
  "synopsis": "Based on the novel \"813\" by Maurice Leblanc.",
  "title": {
    "jp": "Kaitou Lupin: 813 no Nazo"
  },
  "releasedAt": "1979-05-05T00:00:00.000Z",
  "finishedAt": "1979-05-05T00:00:00.000Z",
  "kind": "special",
  "status": "finished",
  "rating": "pg",
  "posterUrl": "https://media.kitsu.io/anime/poster_images/9141/original.jpg",
  "categories": [
    "mystery",
    "thievery"
  ],
  "externals": [],
  "relations": {
    "kitsu": "9141",
    "anidb": "3179",
    "anilist/anime": "17403",
    "aozora": "iILfksKAlc",
    "myanimelist/anime": "17403"
  }
}