{
  "slug": "miyuki",
  "synopsis": "Wakamatsu Masato lives with his step-sister, Miyuki, whom he does not have blood relationship with. Their father is always working oversea and left the two of them living by themselves in Toukyou. Miyuki is cute, nice, sensitive and very popular among guys around Masato. Masato has a girlfriend at school whose name is Kajima Miyuki, who is pretty and gentle, the ideal dream of every highschool boy.\n(Source: AnimeNfo)",
  "title": {
    "jp": "Miyuki"
  },
  "releasedAt": "1983-03-31T00:00:00.000Z",
  "finishedAt": "1984-04-20T00:00:00.000Z",
  "kind": "tv",
  "status": "finished",
  "rating": "pg",
  "posterUrl": "https://media.kitsu.io/anime/poster_images/2022/original.jpg",
  "categories": [
    "asia",
    "comedy",
    "coming of age",
    "earth",
    "japan",
    "love polygon",
    "plot continuity",
    "present",
    "romance",
    "school life",
    "shounen",
    "slapstick",
    "slice of life",
    "slow when it comes to love",
    "violent retribution for accidental infringement"
  ],
  "externals": [],
  "relations": {
    "kitsu": "2022",
    "anidb": "925",
    "anilist/anime": "2231",
    "aozora": "On3lh5Us62",
    "myanimelist/anime": "2231",
    "thetvdb": "258267/1",
    "thetvdb/series": "258267",
    "trakt": "67101"
  }
}