{
  "slug": "luger-code-1951",
  "synopsis": "The story follows a young genius university professor who is able to learn any language. He is asked to decipher a code used in wireless communication: the Luger Code, developed by werewolves, enemies to mankind. Startled to find that he cannot decipher the code and desperate to study it, the professor embarks on a journey to capture a living werewolf to aid him.\n(Source: LiveChart)",
  "title": {
    "jp": "Luger Code 1951"
  },
  "releasedAt": "2016-10-22T00:00:00.000Z",
  "finishedAt": "2016-10-22T00:00:00.000Z",
  "kind": "special",
  "status": "finished",
  "rating": "pg",
  "posterUrl": "https://media.kitsu.io/anime/poster_images/11379/original.png",
  "categories": [
    "action",
    "contemporary fantasy",
    "fantasy",
    "violence"
  ],
  "externals": [],
  "relations": {
    "kitsu": "11379",
    "anidb": "11594",
    "anilist/anime": "21674",
    "aozora": "keUQkUY8md",
    "myanimelist/anime": "31598",
    "thetvdb": "314479",
    "trakt": "106523"
  }
}