{
  "slug": "to-heart-2-special",
  "synopsis": "Special recap episode #11.5.",
  "title": {
    "jp": "To Heart 2 Special"
  },
  "releasedAt": "2005-12-24T00:00:00.000Z",
  "finishedAt": "2005-12-24T00:00:00.000Z",
  "kind": "special",
  "status": "finished",
  "rating": "pg",
  "posterUrl": "https://media.kitsu.io/anime/poster_images/1459/original.jpg",
  "coverUrl": "https://media.kitsu.io/anime/cover_images/1459/original.jpg",
  "categories": [
    "drama",
    "romance",
    "school life"
  ],
  "externals": [],
  "relations": {
    "kitsu": "1459",
    "anilist/anime": "1624",
    "aozora": "fcO7pQeybv",
    "myanimelist/anime": "1624"
  }
}