[
  {
    "id": "157751",
    "title": {},
    "season": 1,
    "number": 1,
    "content": {}
  },
  {
    "id": "157752",
    "title": {},
    "season": 1,
    "number": 2,
    "content": {}
  },
  {
    "id": "157753",
    "title": {},
    "season": 1,
    "number": 3,
    "content": {}
  },
  {
    "id": "157754",
    "title": {},
    "season": 1,
    "number": 4,
    "content": {}
  },
  {
    "id": "157755",
    "title": {},
    "season": 1,
    "number": 5,
    "content": {}
  },
  {
    "id": "157756",
    "title": {},
    "season": 1,
    "number": 6,
    "content": {}
  }
]