{
  "slug": "totsuzen-girl",
  "synopsis": "Music video for the song Totsuzen GIRL by You Watanabe.",
  "title": {
    "jp": "Totsuzen GIRL"
  },
  "releasedAt": "2021-04-17T00:00:00.000Z",
  "finishedAt": "2021-04-17T00:00:00.000Z",
  "kind": "music",
  "status": "finished",
  "rating": "r",
  "posterUrl": "https://media.kitsu.io/anime/poster_images/44450/original.png",
  "categories": [
    "idol",
    "music"
  ],
  "externals": [],
  "relations": {
    "kitsu": "44450",
    "anilist/anime": "132936"
  }
}